murasame_pp_py-1.0.2.dist-info/METADATA
murasame_pp_py-1.0.2.dist-info/WHEEL
murasame_pp_py-1.0.2.dist-info/license_files/LICENSE
murasame_pp_py/__init__.py
murasame_pp_py/__init__.pyi
murasame_pp_py/py.typed
murasame_pp_py/murasame_pp_py.cpython-37m-darwin.so
murasame_pp_py-1.0.2.dist-info/RECORD
